lucide_fasthtml/__about__.py
lucide_fasthtml/__init__.py
lucide_fasthtml/core.py
lucide_fasthtml/lucide.py
lucide_fasthtml/lucide.pyi
lucide_fasthtml-0.0.8.dist-info/METADATA
lucide_fasthtml-0.0.8.dist-info/WHEEL
lucide_fasthtml-0.0.8.dist-info/licenses/LICENSE.txt
lucide_fasthtml-0.0.8.dist-info/RECORD
