Metadata-Version: 2.3
Name: lucide-fasthtml
Version: 0.0.8
Summary: Lucide icons for FastHTML
Project-URL: Documentation, https://github.com/curtis-allan/lucide-fasthtml#readme
Project-URL: Issues, https://github.com/curtis-allan/lucide-fasthtml/issues
Project-URL: Source, https://github.com/curtis-allan/lucide-fasthtml
Author-email: Curtis Allan <curtisjallan98@gmail.com>
License-Expression: MIT
License-File: LICENSE.txt
Keywords: fasthtml,icons,lucide
Classifier: Development Status :: 4 - Beta
Classifier: Programming Language :: Python
Classifier: Programming Language :: Python :: 3.8
Classifier: Programming Language :: Python :: 3.9
Classifier: Programming Language :: Python :: 3.10
Classifier: Programming Language :: Python :: 3.11
Classifier: Programming Language :: Python :: 3.12
Classifier: Programming Language :: Python :: Implementation :: CPython
Classifier: Programming Language :: Python :: Implementation :: PyPy
Requires-Python: >=3.8
Requires-Dist: python-fasthtml>=0.5.2
Requires-Dist: requests>=2.32.2
